flask_dry_transaction.py
setup.cfg
setup.py
Flask_Dry_Transaction.egg-info/PKG-INFO
Flask_Dry_Transaction.egg-info/SOURCES.txt
Flask_Dry_Transaction.egg-info/dependency_links.txt
Flask_Dry_Transaction.egg-info/top_level.txt