Metadata-Version: 1.1
Name: Flask-Dry-Transaction
Version: 0.1.0
Summary: A python package implementing the strategy of business transaction in flask microservices developement
Home-page: https://github.com/SOA-KunLin/Flask-Dry-Transaction
Author: Kun-Lin
Author-email: orange6318@hotmail.com
License: MIT
Download-URL: https://github.com/SOA-KunLin/Flask-Dry-Transaction/tarball/0.1.0
Keywords: flask,dry,transaction
Platform: UNKNOWN
